odoo/addons/shopinvader_customer_multi_user_validate/README.rst
odoo/addons/shopinvader_customer_multi_user_validate/__init__.py
odoo/addons/shopinvader_customer_multi_user_validate/__manifest__.py
odoo/addons/shopinvader_customer_multi_user_validate/i18n/shopinvader_customer_multi_user_validate.pot
odoo/addons/shopinvader_customer_multi_user_validate/readme/CONTRIBUTORS.rst
odoo/addons/shopinvader_customer_multi_user_validate/readme/CREDITS.rst
odoo/addons/shopinvader_customer_multi_user_validate/readme/DESCRIPTION.rst
odoo/addons/shopinvader_customer_multi_user_validate/services/__init__.py
odoo/addons/shopinvader_customer_multi_user_validate/services/user_management.py
odoo/addons/shopinvader_customer_multi_user_validate/static/description/index.html
odoo14_addon_shopinvader_customer_multi_user_validate-14.0.1.1.0.dist-info/METADATA
odoo14_addon_shopinvader_customer_multi_user_validate-14.0.1.1.0.dist-info/WHEEL
odoo14_addon_shopinvader_customer_multi_user_validate-14.0.1.1.0.dist-info/top_level.txt
odoo14_addon_shopinvader_customer_multi_user_validate-14.0.1.1.0.dist-info/RECORD
