Metadata-Version: 2.1
Name: odoo14-addon-shopinvader-customer-multi-user-validate
Version: 14.0.1.1.0
Summary: Glue module for `shopinvader_customer_validate` and `shopinvader_customer_multi_user`.
Home-page: https://github.com/shopinvader/odoo-shopinvader
Author: Camptocamp SA
License: AGPL-3
Platform: UNKNOWN
Classifier: Programming Language :: Python
Classifier: Framework :: Odoo
Classifier: License :: OSI Approved :: GNU Affero General Public License v3
Requires-Python: >=3.6
Requires-Dist: odoo14-addon-shopinvader-customer-multi-user
Requires-Dist: odoo14-addon-shopinvader-customer-validate
Requires-Dist: odoo (<14.1dev,>=14.0a)
